airflow_helper/__init__.py
airflow_helper/api.py
airflow_helper/cli.py
airflow_helper/core.py
airflow_helper/creator.py
airflow_helper/models.py
airflow_helper/reader.py
airflow_helper/remote.py
airflow_helper/settings.py
airflow_helper-0.2.0.dist-info/LICENSE
airflow_helper-0.2.0.dist-info/METADATA
airflow_helper-0.2.0.dist-info/WHEEL
airflow_helper-0.2.0.dist-info/entry_points.txt
airflow_helper-0.2.0.dist-info/RECORD
