Metadata-Version: 2.1
Name: airflow-helper
Version: 0.2.0
Summary: 
Home-page: https://github.com/xnuinside/airflow-helper
License: MIT
Author: Iuliia Volkova
Author-email: xnuinside@gmail.com
Requires-Python: >=3.8,<3.12
Classifier: License :: OSI Approved :: MIT License
Classifier: Programming Language :: PL/SQL
Classifier: Programming Language :: Python :: 3
Classifier: Programming Language :: Python :: 3.8
Classifier: Programming Language :: Python :: 3.9
Classifier: Programming Language :: Python :: 3.10
Classifier: Programming Language :: Python :: 3.11
Classifier: Programming Language :: SQL
Classifier: Topic :: Software Development
Classifier: Topic :: Software Development :: Libraries
Classifier: Topic :: Software Development :: Libraries :: Python Modules
Classifier: Topic :: Utilities
Requires-Dist: apache-airflow-client (>=2.7.3,<3.0.0)
Requires-Dist: pydantic (>=2.5.1,<3.0.0)
Requires-Dist: pydantic-settings (>=2.1.0,<3.0.0)
Requires-Dist: pyyaml (>=6.0.1,<7.0.0)
Requires-Dist: typer (>=0.9.0,<0.10.0)
Project-URL: Repository, https://github.com/xnuinside/airflow-helper
